hfive/__init__.py
hfive/common.py
hfive/main.py
hfive/widgets.py
hfive-0.1.2.dist-info/LICENSE
hfive-0.1.2.dist-info/METADATA
hfive-0.1.2.dist-info/WHEEL
hfive-0.1.2.dist-info/entry_points.txt
hfive-0.1.2.dist-info/top_level.txt
hfive-0.1.2.dist-info/RECORD
