Metadata-Version: 2.1
Name: hfive
Version: 0.1.2
Summary: A simple TUI for viewing HDF5 files.
Author-email: Flavio Lorez <florez@ethz.ch>
License: Copyright (c) 2024 Flavio Lorez
Project-URL: repository, https://gitlab.com/zrlf/hfive
Project-URL: changelog, https://gitlab.com/zrlf/hfive/-/tree/main/CHANGELOG.md
Keywords: HDF5,terminal,user interface,bamboost
Classifier: License :: OSI Approved :: MIT License
Classifier: Programming Language :: Python
Classifier: Programming Language :: Python :: 3
Requires-Python: >=3.7
License-File: LICENSE
Requires-Dist: urwid
Requires-Dist: h5py
Requires-Dist: numpy
